LICENSE
README.md
setup.py
jina_sagemaker/__init__.py
jina_sagemaker/client.py
jina_sagemaker/helper.py
jina_sagemaker.egg-info/PKG-INFO
jina_sagemaker.egg-info/SOURCES.txt
jina_sagemaker.egg-info/dependency_links.txt
jina_sagemaker.egg-info/not-zip-safe
jina_sagemaker.egg-info/requires.txt
jina_sagemaker.egg-info/top_level.txt
tests/__init__.py
tests/test_client.py
tests/test_helper.py