Metadata-Version: 2.1
Name: jina-sagemaker
Version: 0.0.31
Summary: Python library for the Jina endpoints in AWS Sagemaker
Home-page: https://github.com/jina-ai/jina-sagemaker
Download-URL: https://github.com/jina-ai/jina-sagemaker/tags
Author: Jina AI
Author-email: hello@jina.ai
License: Apache 2.0
Classifier: Programming Language :: Python :: 3
Classifier: License :: OSI Approved :: Apache Software License
Classifier: Operating System :: OS Independent
Provides-Extra: test
License-File: LICENSE
